adder.v
module adder(a,b,c,sum,carry);
  input a,b,c;
  output sum,carry;
  assign sum=a^b^c;
  assign carry=a&b|b&c|c&a;
endmodule

adder_tb.v
`timescale 10ns/1ns
module adder_tb;
reg a,b,c;
wire sum,carry;
  adder uut(.a(a), .b(b), .c(c), .sum(sum), .carry(carry));
initial begin 
  $dumpfile("adder_wave.vcd");
  $dumpvars(0,adder_tb);
a=0; b=0; c=0;
#5 a=0; b=0; c=1;
#5 a=0; b=1; c=0;
#5 a=0; b=1; c=1;
#5 a=1; b=0; c=0;
#5 a=1; b=0; c=1;
#5 a=1; b=1; c=0;
#5 a=1; b=1; c=1;
#5 $finish;
end
endmodule

adder_wave.vcd
$date
	Sun Mar 01 22:12:51 2026
$end
$version
	Icarus Verilog
$end
$timescale
	1ns
$end
$scope module adder_tb $end
$var wire 1 ! sum $end
$var wire 1 " carry $end
$var reg 1 # a $end
$var reg 1 $ b $end
$var reg 1 % c $end
$scope module uut $end
$var wire 1 # a $end
$var wire 1 $ b $end
$var wire 1 % c $end
$var wire 1 " carry $end
$var wire 1 ! sum $end
$upscope $end
$upscope $end
$enddefinitions $end
#0
$dumpvars
0%
0$
0#
0"
0!
$end
#50
1!
1%
#100
0%
1$
#150
1"
0!
1%
#200
0"
1!
0%
0$
1#
#250
1"
0!
1%
#300
0%
1$
#350
1!
1%
